{"expireTime":9007200920746346000,"key":"f580c777171cb2a92d758aa60d30d024","val":{"name":"IMAGE_PROCESSING","inputPaths":["/Users/gabriel/Documents/alchemy-dark/src/data/project/images/project-03.jpg"],"outputDir":"/Users/gabriel/Documents/alchemy-dark/public/static/f2faf3ba217badb7bb879e41d747ca51","args":{"isLazy":false,"operations":[{"outputPath":"0d590/project-03.jpg","args":{"height":250,"width":480,"cropFocus":17,"toFormat":"jpg","quality":100,"fit":"cover","background":"rgba(0,0,0,1)"}},{"outputPath":"e012a/project-03.jpg","args":{"height":500,"width":960,"cropFocus":17,"toFormat":"jpg","quality":100,"fit":"cover","background":"rgba(0,0,0,1)"}},{"outputPath":"60b1b/project-03.jpg","args":{"height":563,"width":1080,"cropFocus":17,"toFormat":"jpg","quality":100,"fit":"cover","background":"rgba(0,0,0,1)"}}],"pluginOptions":{"base64Width":20,"forceBase64Format":"","useMozJpeg":false,"stripMetadata":true,"lazyImageGeneration":true,"defaultQuality":50,"failOnError":true,"plugins":[]}}}}